hlpl_character/__init__.py
hlpl_character/__main__.py
hlpl_character/setup.cfg
hlpl_character-1.0.0.dist-info/LICENSE
hlpl_character-1.0.0.dist-info/METADATA
hlpl_character-1.0.0.dist-info/WHEEL
hlpl_character-1.0.0.dist-info/entry_points.txt
hlpl_character-1.0.0.dist-info/top_level.txt
hlpl_character-1.0.0.dist-info/RECORD
